numerical_methods/__init__.py
numerical_methods/data/__init__.py
numerical_methods/data/numerical_methods_presentation.pdf
enm_penm-0.1.dist-info/METADATA
enm_penm-0.1.dist-info/WHEEL
enm_penm-0.1.dist-info/top_level.txt
enm_penm-0.1.dist-info/RECORD
