Metadata-Version: 2.4
Name: enm-penm
Version: 0.1
Summary: Библиотека с материалами по численным методам
Author: Ваше имя
Requires-Dist: numpy
Dynamic: author
Dynamic: requires-dist
Dynamic: summary
